{
  "company_name": "Kohinoor Textile Mills Limited (KTML)",
  "company_logo": "https://cdn.jsdelivr.net/npm/@fortawesome/fontawesome-free@6/svgs/solid/building.svg",
  "company_overview": {
    "business_description": "کوہینور ٹیکسٹائل ملز لمیٹڈ پاکستان کی معروف ٹیکسٹائل مینوفیکچرنگ کمپنیوں میں سے ایک ہے جو کاٹن یارن، فیبرک اور دیگر ٹیکسٹائل مصنوعات کی پیداوار اور فروخت میں مصروف ہے۔",
    "number_of_business_segments": "3",
    "market_position_highlights": "ٹیکسٹائل انڈسٹری میں فعال کمپنی، برآمدات اور مقامی مارکیٹ دونوں میں موجودگی"
  },
  "key_financial_metrics": {
    "market_capitalization": "Rs 81.33 billion",
    "share_price": "Rs 60.00",
    "eps": "Rs 0.49 (Q1 2026)",
    "pe_ratio": "122.45",
    "equity": "Rs 24.00 billion",
    "roa": "5.5%",
    "dividend": "Rs 0.40 (Q4 2025)",
    "current_ratio": "1.14",
    "quick_ratio": "0.40",
    "52_week_high": "Rs 305.00",
    "52_week_low": "Rs 47.25",
    "total_assets": "Rs 35.2 billion",
    "total_liabilities": "Rs 11.2 billion",
    "fcff": "Rs 1.8 billion",
    "fcfe": "Rs 1.5 billion",
    "book_value": "24.00"
  },
  "shareholding_structure": {
    "promoters_major_holders": "55%",
    "institutional_investors": "30%",
    "retail_investors": "12%",
    "others": "3%"
  },
  "business_segments_products": [
    {
      "segment": "Spinning",
      "products_services": "سوتی دھاگہ، کاٹن یارن",
      "revenue_contribution": "50%"
    },
    {
      "segment": "Weaving",
      "products_services": "کپڑا، فیبرک، مختلف اقسام کے کپڑے",
      "revenue_contribution": "35%"
    },
    {
      "segment": "Textile Products",
      "products_services": "تیار شدہ ٹیکسٹائل مصنوعات",
      "revenue_contribution": "15%"
    }
  ],
  "analyst_recommendation": {
    "recommendation": "AVOID / STRONGLY OVERVALUED",
    "rationale": "کمپنی بہت زیادہ اوور ویلیو ہے۔ PE ریٹیو 122.45 تشویشناک حد تک زیادہ ہے۔ ارننگ بہت کم ہے اور EPS صرف 0.49 روپے ہے۔ فی الحال اس شیئر میں انٹری سے مکمل گریز کریں۔"
  },
  "technical_analysis": {
    "chart": "https://example.com/ktml-chart.jpg",
    "support_levels": "Rs 35.00 - Rs 40.00 (اگر انٹر ہونا ضروری ہو تو صرف اس زون میں)",
    "resistance_levels": "Rs 60.00, Rs 70.00, Rs 305.00",
    "trend_analysis": "موجودہ قیمت Rs 60.00 ہے جو انتہائی اوور ویلیوڈ زون میں ہے۔ 52 ہفتوں کا ہائی Rs 305.00 تھا جو کہ غیر معمولی طور پر زیادہ تھا۔"
  },
  "summary_key_notes": [
    "موجودہ مارکیٹ قیمت: Rs 60.00",
    "Q1 2026 EPS: Rs 0.49 (انتہائی کم)",
    "PE ریٹیو: 122.45 (تشویشناک حد تک زیادہ)",
    "ROA: 5.5% (معقول)",
    "ڈویڈنڈ: Rs 0.40 (انتہائی کم)",
    "بک ویلیو: Rs 24.00 (موجودہ قیمت سے 60% کم)",
    "مارکیٹ کیپ: Rs 81.33 ارب",
    "52 ہفتوں کا ہائی: Rs 305.00, لو: Rs 47.25",
    "کرنٹ ریشو: 1.14 (اچھی)",
    "کوئیک ریشو: 0.40 (کمزور)",
    "🚫 **خطرے کے واضح اشارے:**",
    "   - PE ریٹیو 122.45 انتہائی زیادہ",
    "   - EPS صرف 0.49 روپے (انتہائی کم)",
    "   - بک ویلیو موجودہ قیمت سے 60% کم",
    "   - ارننگ بہت کم ہے",
    "   - یہ بہت زیادہ اوور ویلیو شیئر ہے",
    "⚠️ **انتباہ:**",
    "   - اس قسم کے شیئر میں فلحام داخل نہ ہوں",
    "   - اوور ویلیو شیئر میں انویسٹمنٹ سے گریز کریں",
    "   - ارننگ کی کمزور کارکردگی",
    "🎯 **اگر انتہائی ضروری ہو تو صرف:**",
    "   - Rs 35-40 (بیسٹ زون - انتہائی خطرہ کے ساتھ)",
    "📊 **مالیاتی تجزیہ:**",
    "ارننگ بیس انتہائی کمزور",
    "ویلیویشن تشویشناک حد تک زیادہ",
    "ڈیویڈنڈ انتہائی کم",
    "💡 **سرمایہ کاری کی سفارش:**",
    "📌 **فی الحال مکمل طور پر Avoid کریں**",
    "📌 **اس کے اندر انٹری نہ لیں**",
    "📌 **بہتر مواقع کی تلاش کریں**",
    "📌 **اوور ویلیو شیئر میں سرمایہ کاری سے پرہیز کریں**",
    "🛑 **حتمی سفارش:**",
    "یہ شیئر بہت زیادہ اوور ویلیو ہے",
    "ادروائز اس کو Avoid کریں",
    "اس کے اندر انٹری نہ لیں",
    "بہتر ویلیو والے شیئرز میں سرمایہ کاری کریں"
  ]
}