{
  "company_name": "Service Textile Industry",
  "company_logo": "https://example.com/service-textile-logo.png",
  
  "company_overview": {
    "business_description": "سروس ٹیکسٹائل انڈسٹری پاکستان کی ایک ٹیکسٹائل مینوفیکچرنگ کمپنی ہے جو کپڑے کی تیاری، پروسیسنگ اور ٹیکسٹائل مصنوعات کی مینوفیکچرنگ میں مہارت رکھتی ہے۔ کمپنی مختلف قسم کے ٹیکسٹائل پراڈکٹس مارکیٹ میں فراہم کرتی ہے۔",
    "number_of_business_segments": "2",
    "market_position_highlights": "ٹیکسٹائل انڈسٹری کا حصہ، مینوفیکچرنگ یونٹس، مقامی مارکیٹ میں موجودگی"
  },

  "key_financial_metrics": {
    "market_capitalization": "Rs 2.80 billion",
    "share_price": "Rs 40.00",
    "eps": "Rs -0.71 (Q1 2026)",
    "pe_ratio": "-14.12",
    "equity": "Rs 4.50 billion",
    "roa": "-40.32%",
    "dividend": "Rs 0.00 (آخری 2021 میں دیا گیا)",
    "current_ratio": "0.20",
    "quick_ratio": "0.17",
    "52_week_high": "Rs 78.30",
    "52_week_low": "Rs 10.11",
    "total_assets": "Rs 12.00 billion",
    "total_liabilities": "Rs 7.50 billion",
    "fcff": "Rs -1.20 billion",
    "fcfe": "Rs -0.90 billion",
    "book_value": "Rs 72.00"
  },

  "shareholding_structure": {
    "promoters_major_holders": "45%",
    "institutional_investors": "20%",
    "retail_investors": "30%",
    "others": "5%"
  },

  "business_segments_products": [
    {
      "segment": "ٹیکسٹائل مینوفیکچرنگ",
      "products_services": "کپڑے کی تیاری، ٹیکسٹائل پروسیسنگ، فینیکڈ فیبرکس، گارمنٹس",
      "revenue_contribution": "75%"
    },
    {
      "segment": "ٹیکسٹائل ایکسپورٹ",
      "products_services": "برآمداتی ٹیکسٹائل مصنوعات، بین الاقوامی مارکیٹنگ",
      "revenue_contribution": "25%"
    }
  ],

  "analyst_recommendation": {
    "recommendation": "TRADING BUY AT 34, BEST INVESTMENT AT 20-25 (HIGH RISK)",
    "rationale": "کمپنی فی الحال مالی مشکلات کا شکار ہے۔ EPS منفی ہے (-0.71)، ROA منفی ہے (-40.32%)، اور PE ریشو منفی ہے (-14.12)۔ تاہم، بک ویلیو (Rs 72) موجودہ قیمت (Rs 40) سے کافی زیادہ ہے جو انڈر ویلیویشن ظاہر کرتا ہے۔ لیکن مالی صحت کمزور ہے۔ ٹریڈنگ کے لیے Rs 34 اور بہت ہی ریسکی انویسٹمنٹ کے لیے Rs 20-25 بہترین ہیں۔"
  },

  "technical_analysis": {
    "chart": "https://example.com/service-textile-chart.jpg",
    "support_levels": "Rs 20-25 (HIGH RISK INVESTMENT ZONE), Rs 34.00 (ٹریڈنگ سپورٹ)",
    "resistance_levels": "Rs 40.00 (موجودہ قیمت), Rs 78.30 (52 ہفتوں کا ہائی)",
    "trend_analysis": "موجودہ قیمت Rs 40.00 بہترین سرمایہ کاری زون (Rs 20-25) سے اوپر ہے۔ کمپنی کی مالی کارکردگی بہت کمزور ہے۔ بک ویلیو Rs 72 سے کمپنی انڈر ویلیو لگ رہی ہے لیکن منفی EPS اور ROA بڑا خطرہ ہیں۔"
  },

  "summary_key_notes": [
    "موجودہ مارکیٹ قیمت: Rs 40.00",
    "بہترین سرمایہ کاری زون (ہائی رسک): Rs 20-25",
    "ٹریڈنگ کے لیے لیول: Rs 34.00",
    "Q1 2026 EPS: Rs -0.71 (منفی)",
    "PE ریشو: -14.12 (منفی)",
    "آخری ڈیویڈنڈ: 2021 کے چوتھے کوارٹر میں دیا گیا",
    "بک ویلیو: Rs 72.00 (موجودہ قیمت سے 80% زیادہ - انڈر ویلیوڈ)",
    "مارکیٹ کیپ: Rs 2.80 ارب",
    "ایکوئٹی: Rs 4.50 ارب",
    "کل اثاثے: Rs 12.00 ارب",
    "کل واجبات: Rs 7.50 ارب",
    "کل قرضہ (2025 تک): تقریباً Rs 6.00 ارب",
    "فری کیش فلو (FCFF): Rs -1.20 ارب (منفی)",
    "فری کیش فلو برائے حصص دار (FCFE): Rs -0.90 ارب (منفی)",
    "ROA: -40.32% (منفی - تشویشناک)",
    "52 ہفتوں کا ہائی: Rs 78.30, لو: Rs 10.11",
    "کرنٹ ریشو: 0.20 (بہت کم - کمزور)",
    "کوئیک ریشو: 0.17 (بہت کم - 1 ہونا چاہیے)",
    "پروموٹرز/اہم حصص دار: 45%",
    "انسٹی ٹیوشنل سرمایہ کار: 20%",
    "ریٹیل سرمایہ کار: 30%",
    "کمپنی کی عمر: 1980 کی دہائی میں قائم (تقریباً 40 سال پرانی)",
    "مینجمنٹ تجربہ: پرانی مینجمنٹ لیکن مالی مشکلات کا سامنا",
    "کمپنی کا شعبہ: ٹیکسٹائل مینوفیکچرنگ",
    "بنیادی مصنوعات: ٹیکسٹائل مصنوعات، کپڑے، گارمنٹس",
    "کمپنی انڈر ویلیو لگ رہی ہے (بک ویلیو Rs 72 بمقابلہ موجودہ قیمت Rs 40)",
    "لیکن مالی کارکردگی تشویشناک ہے",
    "EPS منفی ہے جو نقصان ظاہر کرتا ہے",
    "ROA منفی ہے جو اثاثوں کے استعمال میں بہت کمزوری",
    "لیکویڈیٹی ریشوز بہت کمزور ہیں (کرنٹ 0.20، کوئیک 0.17)",
    "آخری ڈیویڈنڈ 2021 میں دیا گیا تھا",
    "ٹریڈنگ پوزیشن کے لیے Rs 34 کے قریب خریداری (ہائی رسک)",
    "لمبی مدتی سرمایہ کاری کے لیے Rs 20-25 تک انتظار (بہت ہائی رسک)",
    "کمپنی کو مالی بحران کا سامنا ہے",
    "مارکیٹ کی قیمت 52 ہفتوں کے ہائی سے 49% کم ہے",
    "بک ویلیو موجودہ قیمت سے زیادہ ہونے کے باوجود مالی مشکلات",
    "انویسٹمنٹ کے لیے انتہائی محتاط رہنے کی ضرورت"
  ]
}
